{
    "items": {
        "title": "크기 조절 ",
        "description": "크기 변경을 원할 경우 .pagination-lg 나 .pagination-sm를 추가해 주세요.",
        "code": "<nav aria-label=\"...\">\n  <ul class=\"pagination pagination-lg\">\n    <li class=\"page-item active\" aria-current=\"page\">\n      <span class=\"page-link\">1<\/span>\n    <\/li>\n    <li class=\"page-item\"><a class=\"page-link\" href=\"#\">2<\/a><\/li>\n    <li class=\"page-item\"><a class=\"page-link\" href=\"#\">3<\/a><\/li>\n  <\/ul>\n<\/nav>",
        "updated_at": "2024-08-08 12:54:18"
    }
}