{
    "items": {
        "title": "No Wrap",
        "description": "텍스트가 줄바꿈되는 것을 방지하고 필요한 경우 텍스트가 넘치도록 하려면 text-nowwrap을 사용하십시오.\n",
        "code": "<article class=\"text-nowrap w-40 ...\">\n  <h3>Beloved Manhattan soup stand closes<\/h3>\n  <p>New Yorkers are facing the winter chill with less warmth this year as the city's most revered soup stand unexpectedly shutters, following a series of events that have left the community puzzled.<\/p>\n<\/article>",
        "updated_at": "2024-08-12 17:55:28"
    }
}